onnxruntime/__init__.py
onnxruntime/backend/__init__.py
onnxruntime/backend/backend.py
onnxruntime/backend/backend_rep.py
onnxruntime/capi/__init__.py
onnxruntime/capi/_ld_preload.py
onnxruntime/capi/_pybind_state.py
onnxruntime/capi/build_and_package_info.py
onnxruntime/capi/libonnxruntime_providers_shared.so
onnxruntime/capi/onnxruntime_collect_build_info.py
onnxruntime/capi/onnxruntime_inference_collection.py
onnxruntime/capi/onnxruntime_pybind11_state.so
onnxruntime/capi/onnxruntime_validation.py
onnxruntime/datasets/__init__.py
onnxruntime/datasets/logreg_iris.onnx
onnxruntime/datasets/mul_1.onnx
onnxruntime/datasets/sigmoid.onnx
onnxruntime/quantization/__init__.py
onnxruntime/quantization/calibrate.py
onnxruntime/quantization/qdq_quantizer.py
onnxruntime/quantization/quant_utils.py
onnxruntime/quantization/quantize.py
onnxruntime/quantization/registry.py
onnxruntime/quantization/CalTableFlatBuffers/KeyValue.py
onnxruntime/quantization/CalTableFlatBuffers/TrtTable.py
onnxruntime/quantization/CalTableFlatBuffers/__init__.py
onnxruntime/quantization/operators/__init__.py
onnxruntime/quantization/operators/activation.py
onnxruntime/quantization/operators/attention.py
onnxruntime/quantization/operators/base_operator.py
onnxruntime/quantization/operators/binary_op.py
onnxruntime/quantization/operators/concat.py
onnxruntime/quantization/operators/conv.py
onnxruntime/quantization/operators/direct_q8.py
onnxruntime/quantization/operators/embed_layernorm.py
onnxruntime/quantization/operators/gather.py
onnxruntime/quantization/operators/gavgpool.py
onnxruntime/quantization/operators/lstm.py
onnxruntime/quantization/operators/matmul.py
onnxruntime/quantization/operators/maxpool.py
onnxruntime/quantization/operators/pad.py
onnxruntime/quantization/operators/pooling.py
onnxruntime/quantization/operators/qdq_base_operator.py
onnxruntime/quantization/operators/resize.py
onnxruntime/quantization/operators/split.py
onnxruntime/tools/__init__.py
onnxruntime_lite-1.23.0.dist-info/METADATA
onnxruntime_lite-1.23.0.dist-info/WHEEL
onnxruntime_lite-1.23.0.dist-info/top_level.txt
onnxruntime_lite-1.23.0.dist-info/RECORD
