Metadata-Version: 2.4
Name: onnxruntime-lite
Version: 1.23.0
Summary: Lightweight ONNX Runtime fork (12MB) for serverless environments
Author: JacquieAM
License: Apache 2.0
Classifier: Programming Language :: Python :: 3.12
Classifier: License :: OSI Approved :: MIT License
Classifier: Operating System :: OS Independent
Requires-Python: >=3.12
Dynamic: author
Dynamic: classifier
Dynamic: license
Dynamic: requires-python
Dynamic: summary
